emskaffolden/__init__.py
emskaffolden/__main__.py
emskaffolden/cli.py
emskaffolden/files.py
emskaffolden/skaffold.py
emskaffolden/builtin-templates/django-app/default.vars.yaml
emskaffolden/builtin-templates/django-app/development.vars.yaml
emskaffolden/builtin-templates/django-app/example.vars.yaml
emskaffolden/builtin-templates/django-app/ingress.in.yaml
emskaffolden/builtin-templates/django-app/skaffold.in.yaml
emskaffolden/builtin-templates/django-app/template.in.yaml
emskaffolden/builtin-templates/django-app/gunicorn/deployment.in.yaml
emskaffolden/builtin-templates/django-app/gunicorn/secret.in.yaml
emskaffolden/builtin-templates/django-app/gunicorn/service.in.yaml
emskaffolden/builtin-templates/django-app/postgres/deployment.in.yaml
emskaffolden/builtin-templates/django-app/postgres/pvc.in.yaml
emskaffolden/builtin-templates/django-app/postgres/secret.in.yaml
emskaffolden/builtin-templates/django-app/postgres/service.in.yaml
emskaffolden/builtin-templates/node-app/default.vars.yaml
emskaffolden/builtin-templates/node-app/development.vars.yaml
emskaffolden/builtin-templates/node-app/example.vars.yaml
emskaffolden/builtin-templates/node-app/ingress.in.yaml
emskaffolden/builtin-templates/node-app/skaffold.in.yaml
emskaffolden/builtin-templates/node-app/template.in.yaml
emskaffolden/builtin-templates/node-app/node/deployment.in.yaml
emskaffolden/builtin-templates/node-app/node/secret.in.yaml
emskaffolden/builtin-templates/node-app/node/service.in.yaml
emskaffolden/builtin-templates/node-app/postgres/deployment.in.yaml
emskaffolden/builtin-templates/node-app/postgres/pvc.in.yaml
emskaffolden/builtin-templates/node-app/postgres/secret.in.yaml
emskaffolden/builtin-templates/node-app/postgres/service.in.yaml
emskaffolden-0.3.0.dist-info/METADATA
emskaffolden-0.3.0.dist-info/WHEEL
emskaffolden-0.3.0.dist-info/entry_points.txt
emskaffolden-0.3.0.dist-info/licenses/LICENSE
emskaffolden-0.3.0.dist-info/RECORD
