Metadata-Version: 2.4
Name: emskaffolden
Version: 0.3.0
Summary: Use Skaffold with Emrichen templates
Project-URL: Homepage, http://github.com/con2/emskaffolden
Author-email: Santtu Pajukanta <santtu@pajukanta.fi>
License-Expression: MIT
License-File: LICENSE
Requires-Dist: emrichen
Requires-Dist: jsonpath-rw~=1.4.0
Requires-Dist: pyaml
Requires-Dist: pyyaml
